enigma_machine_german/__init__.py
enigma_machine_german/enigma_machine_german.py
enigma_machine_german/test.py
enigma_machine_german-0.4.0.dist-info/METADATA
enigma_machine_german-0.4.0.dist-info/WHEEL
enigma_machine_german-0.4.0.dist-info/top_level.txt
enigma_machine_german-0.4.0.dist-info/RECORD
